Metadata-Version: 1.0
Name: lupascua-wild
Version: 0.1
Summary: Gaussian and Binomial distributions
Home-page: UNKNOWN
Author: Andreea Lupascu
Author-email: anamaria-andreea.lupascu@boehringer-ingelheim.com
License: UNKNOWN
Platform: UNKNOWN
